lightweight_agent/__init__.py
lightweight_agent/exceptions.py
lightweight_agent/models.py
lightweight_agent/utils.py
lightweight_agent/agent/__init__.py
lightweight_agent/agent/message.py
lightweight_agent/agent/pretty_print.py
lightweight_agent/agent/prompt_builder.py
lightweight_agent/agent/react_agent.py
lightweight_agent/agent/todo_based_agent.py
lightweight_agent/agent/extension/__init__.py
lightweight_agent/agent/extension/citation_agent.py
lightweight_agent/agent/extension/figure_agent.py
lightweight_agent/agent/extension/matplotlib_fix_agent.py
lightweight_agent/agent/extension/polish_agent.py
lightweight_agent/agent/extension/proposal_agent.py
lightweight_agent/agent/extension/revision_agent.py
lightweight_agent/agent/extension/discarded/__init__.py
lightweight_agent/agent/extension/discarded/image_edit_agent.py
lightweight_agent/agent/extension/discarded/table_master_agent.py
lightweight_agent/clients/__init__.py
lightweight_agent/clients/anthropic_client.py
lightweight_agent/clients/banana_image_client.py
lightweight_agent/clients/base.py
lightweight_agent/clients/openai_client.py
lightweight_agent/session/__init__.py
lightweight_agent/session/history.py
lightweight_agent/session/session.py
lightweight_agent/tools/__init__.py
lightweight_agent/tools/base.py
lightweight_agent/tools/registry.py
lightweight_agent/tools/builtin/__init__.py
lightweight_agent/tools/builtin/batch_edit_tool.py
lightweight_agent/tools/builtin/create_todo_list_tool.py
lightweight_agent/tools/builtin/edit_tool.py
lightweight_agent/tools/builtin/image_edit_tool.py
lightweight_agent/tools/builtin/list_dir_tool.py
lightweight_agent/tools/builtin/md_to_pdf_tool.py
lightweight_agent/tools/builtin/read_tool.py
lightweight_agent/tools/builtin/run_node_file_tool.py
lightweight_agent/tools/builtin/run_python_file_tool.py
lightweight_agent/tools/builtin/save_important_artifacts_tool.py
lightweight_agent/tools/builtin/update_todo_status_tool.py
lightweight_agent/tools/builtin/write_tool.py
lightweight_agent-0.1.8.dist-info/licenses/LICENSE
lightweight_agent-0.1.8.dist-info/METADATA
lightweight_agent-0.1.8.dist-info/WHEEL
lightweight_agent-0.1.8.dist-info/top_level.txt
lightweight_agent-0.1.8.dist-info/RECORD
