Metadata-Version: 2.4
Name: lightweight-agent
Version: 0.1.8
Summary: A lightweight LLM agent framework supporting async OpenAI and Anthropic APIs with ReAct agents, TODO-based agents, and built-in tools
Author: Lightweight Agent Contributors
License: MIT
Project-URL: Homepage, https://github.com/mbt1909432/lightweight-agent
Project-URL: Documentation, https://github.com/mbt1909432/lightweight-agent#readme
Project-URL: Repository, https://github.com/mbt1909432/lightweight-agent
Project-URL: Issues, https://github.com/mbt1909432/lightweight-agent/issues
Keywords: llm,openai,anthropic,async,streaming,ai,agent,react,todo
Classifier: Development Status :: 3 - Alpha
Classifier: Intended Audience :: Developers
Classifier: License :: OSI Approved :: MIT License
Classifier: Programming Language :: Python :: 3
Classifier: Programming Language :: Python :: 3.8
Classifier: Programming Language :: Python :: 3.9
Classifier: Programming Language :: Python :: 3.10
Classifier: Programming Language :: Python :: 3.11
Classifier: Programming Language :: Python :: 3.12
Classifier: Topic :: Software Development :: Libraries :: Python Modules
Classifier: Topic :: Scientific/Engineering :: Artificial Intelligence
Requires-Python: >=3.8
License-File: LICENSE
Requires-Dist: openai>=1.0.0
Requires-Dist: anthropic>=0.18.0
Requires-Dist: httpx>=0.27.2
Requires-Dist: rich>=13.0.0
Requires-Dist: PyYAML>=6.0
Requires-Dist: matplotlib>=3.7.0
Requires-Dist: numpy>=1.24.0
Requires-Dist: seaborn>=0.12.0
Requires-Dist: plotly>=5.14.0
Requires-Dist: pandas>=2.0.0
Requires-Dist: pillow>=10.0.0
Requires-Dist: google-genai>=1.56.0
Requires-Dist: tenacity>=9.1.2
Requires-Dist: markdown-pdf>=1.10
Provides-Extra: dev
Requires-Dist: pytest>=7.0.0; extra == "dev"
Requires-Dist: pytest-asyncio>=0.21.0; extra == "dev"
Requires-Dist: black>=23.0.0; extra == "dev"
Requires-Dist: ruff>=0.1.0; extra == "dev"
Dynamic: license-file
